photon/__init__.py
photon/config.py
photon/logger.py
photon/photon.py
photon/processor.py
photon/providers/__init__.py
photon/providers/openai.py
photon/tests/__init__.py
photon/tests/test_openai.py
photon/tests/providers/__init__.py
photon/tests/providers/test_openai.py
photondemo-0.0.16.dist-info/METADATA
photondemo-0.0.16.dist-info/WHEEL
photondemo-0.0.16.dist-info/top_level.txt
photondemo-0.0.16.dist-info/RECORD
